a3rt_talkpy/__init__.py
a3rt_talkpy/asyncclient.py
a3rt_talkpy/client.py
a3rt_talkpy/exception.py
a3rt_talkpy/response.py
a3rt_talkpy-1.0.2.dist-info/LICENSE
a3rt_talkpy-1.0.2.dist-info/METADATA
a3rt_talkpy-1.0.2.dist-info/WHEEL
a3rt_talkpy-1.0.2.dist-info/top_level.txt
a3rt_talkpy-1.0.2.dist-info/RECORD
