Metadata-Version: 2.1
Name: a3rt-talkpy
Version: 1.0.2
Summary: A3RT Talk API wrapper for Python
Home-page: https://github.com/nattyan-tv/a3rt-talkpy
Author: NattyanTV
License: UNKNOWN
Platform: UNKNOWN
Classifier: Programming Language :: Python :: 3.10
Classifier: License :: OSI Approved :: MIT License
License-File: LICENSE
Requires-Dist: requests
Requires-Dist: asyncio
Requires-Dist: aiohttp
